spiral/__init__.py
spiral/cli.py
spiral/data/__init__.py
spiral/data/augment.py
spiral/export.py
spiral/hypergrad.py
spiral/inference.py
spiral/tests/__init__.py
spiral/tests/objectives.py
spiraltorch/__init__.py
spiraltorch/__init__.pyi
spiraltorch/_meta.py
spiraltorch/_zspace_aliases.py
spiraltorch/ecosystem.py
spiraltorch/elliptic.py
spiraltorch/kdsl_trace.py
spiraltorch/optim.py
spiraltorch/py.typed
spiraltorch/spiralk.pyi
spiraltorch/spiraltorch.abi3.so
spiraltorch/trainer_trace.py
spiraltorch/zspace_atlas.py
spiraltorch/zspace_inference.py
spiraltorch/zspace_live.py
spiraltorch/zspace_trace.py
spiraltorch-0.3.9.dist-info/METADATA
spiraltorch-0.3.9.dist-info/WHEEL
spiraltorch-0.3.9.dist-info/entry_points.txt
spiraltorch-0.3.9.dist-info/RECORD
