Metadata-Version: 2.4
Name: spiraltorch
Version: 0.3.9
Classifier: Programming Language :: Python
Classifier: Programming Language :: Rust
Classifier: License :: OSI Approved :: GNU Affero General Public License v3 or later (AGPLv3+)
Classifier: Operating System :: OS Independent
Summary: Rust-first learning primitives for SpiralTorch
Author: Ryo ∴ SpiralArchitect
License: AGPL-3.0-or-later
Requires-Python: >=3.8
Project-URL: Homepage, https://github.com/RyoSpiralArchitect/SpiralTorch
Project-URL: Source, https://github.com/RyoSpiralArchitect/SpiralTorch
